zpllibrary/__init__.py
zpllibrary/barcodes.py
zpllibrary/downloads.py
zpllibrary/elements.py
zpllibrary/graphics.py
zpllibrary/models.py
zpllibrary/rendering.py
zpllibrary/shared.py
zpllibrary-1.0.3.dist-info/LICENSE
zpllibrary-1.0.3.dist-info/METADATA
zpllibrary-1.0.3.dist-info/WHEEL
zpllibrary-1.0.3.dist-info/top_level.txt
zpllibrary-1.0.3.dist-info/RECORD
